pylst/__init__.py
pylst/exceptions.py
pylst/pylst.py
pylst/runner.py
pylst/utils.py
pylst/emissivity/__init__.py
pylst/emissivity/algorithms.py
pylst/emissivity/emissivity.py
pylst/ml/__init__.py
pylst/ml/ml.py
pylst/normalization/__init__.py
pylst/normalization/normalizer.py
pylst/open/__init__.py
pylst/open/landsat_downloader.py
pylst/open/opener.py
pylst/open/remopener.py
pylst/spatial_analysis/__init__.py
pylst/spatial_analysis/changedet.py
pylst/spatial_analysis/zonstat.py
pylst/temperature/__init__.py
pylst/temperature/brightness_temperature.py
pylst/temperature/temperature.py
pylst/temperature/utils.py
pylst/temperature/algorithms/__init__.py
pylst/temperature/algorithms/mono_window.py
pylst/temperature/algorithms/split_window/__init__.py
pylst/temperature/algorithms/split_window/algorithms.py
pylst/visualization/__init__.py
pylst/visualization/plotter.py
pylst-0.0.2.dist-info/LICENSE
pylst-0.0.2.dist-info/METADATA
pylst-0.0.2.dist-info/WHEEL
pylst-0.0.2.dist-info/top_level.txt
pylst-0.0.2.dist-info/RECORD
