Metadata-Version: 2.1
Name: pylst
Version: 0.0.2
Summary: A Python package for processing and visualizing Landsat LST data.
Home-page: https://github.com/pylst/lst
Author: Azad Rasul
Author-email: azad.rasul@soran.edu.iq
License: MIT
Keywords: Land Surface Temperature (LST),Image processing,Landsat,Remote Sensing,Thermal Satellite images
Classifier: Development Status :: 3 - Alpha
Classifier: Intended Audience :: Science/Research
Classifier: Topic :: Software Development :: Build Tools
Classifier: Programming Language :: Python :: 3.9
Classifier: Natural Language :: English
Requires-Python: >=3.9
License-File: LICENSE
Requires-Dist: numpy (>=1.0)
Requires-Dist: pandas (>=1.4.4)
Requires-Dist: rasterio (>=1.0.0)
Requires-Dist: GDAL (>=2.0.0)
Requires-Dist: geemap (>=0.30.4)
Requires-Dist: ee (>=0.2)
Requires-Dist: opencv-python (>=4.7.0.72)
Requires-Dist: scikit-learn (>=1.0.2)
Requires-Dist: matplotlib (>=3.5.2)
